data_alfred/__init__.py
data_alfred/creator.py
data_alfred-0.2.4.dist-info/LICENSE
data_alfred-0.2.4.dist-info/METADATA
data_alfred-0.2.4.dist-info/WHEEL
data_alfred-0.2.4.dist-info/top_level.txt
data_alfred-0.2.4.dist-info/RECORD
