Metadata-Version: 2.1
Name: data-alfred
Version: 0.2.4
Summary: This is a package for creating a data science project structure
Home-page: https://github.com/TOTVS-Privacidade-de-Dados/data-alfred
Author: Alestan Alves
Author-email: alestan.silva@totvs.com.br
Classifier: Development Status :: 3 - Alpha
Classifier: Intended Audience :: Developers
Classifier: Natural Language :: Portuguese
Classifier: Programming Language :: Python :: 3
Classifier: Programming Language :: Python :: 3.6
Classifier: Programming Language :: Python :: 3.7
Classifier: Programming Language :: Python :: 3.8
Classifier: Programming Language :: Python :: 3.9
Classifier: Programming Language :: Python :: 3.10
Classifier: Programming Language :: Python :: 3.11
Classifier: License :: OSI Approved :: MIT License
Classifier: Operating System :: OS Independent
Requires-Python: >=3.6
License-File: LICENSE
